mclip_anytorch-1.0.13.data/data/README.md
multilingual_clip/Config_MCLIP.py
multilingual_clip/__init__.py
multilingual_clip/legacy_multilingual_clip.py
multilingual_clip/pt_multilingual_clip.py
multilingual_clip/tf_multilingual_clip.py
multilingual_clip/TeacherLearning/ConvertTrainingModelToPT.py
multilingual_clip/TeacherLearning/Dataset.py
multilingual_clip/TeacherLearning/Training.py
multilingual_clip/TeacherLearning/TrainingModel.py
multilingual_clip/TeacherLearning/Utils.py
multilingual_clip/TeacherLearning/__init__.py
mclip_anytorch-1.0.13.dist-info/METADATA
mclip_anytorch-1.0.13.dist-info/WHEEL
mclip_anytorch-1.0.13.dist-info/top_level.txt
mclip_anytorch-1.0.13.dist-info/RECORD
